{ "class":"map",
 "compressionlevel":-1,
 "height":20,
 "infinite":false,
 "layers":[
        {
         "id":5,
         "layers":[
                {
                 "draworder":"topdown",
                 "id":8,
                 "name":"Bottom",
                 "objects":[
                        {
                         "height":0,
                         "id":30,
                         "name":"",
                         "polygon":[
                                {
                                 "x":13.3333333333333,
                                 "y":-28.6666666666667
                                }, 
                                {
                                 "x":-32,
                                 "y":-100.5
                                }, 
                                {
                                 "x":30.5,
                                 "y":-303.5
                                }, 
                                {
                                 "x":127,
                                 "y":-369
                                }, 
                                {
                                 "x":249.5,
                                 "y":-353.5
                                }, 
                                {
                                 "x":244,
                                 "y":-254
                                }, 
                                {
                                 "x":213,
                                 "y":-133.5
                                }, 
                                {
                                 "x":158.5,
                                 "y":-36.8333333333334
                                }],
                         "rotation":0,
                         "type":"region",
                         "visible":true,
                         "width":0,
                         "x":204,
                         "y":645
                        }, 
                        {
                         "height":0,
                         "id":31,
                         "name":"",
                         "point":true,
                         "rotation":0,
                         "type":"guard",
                         "visible":true,
                         "width":0,
                         "x":315.5,
                         "y":488.5
                        }, 
                        {
                         "height":0,
                         "id":32,
                         "name":"",
                         "point":true,
                         "rotation":0,
                         "type":"node",
                         "visible":true,
                         "width":0,
                         "x":336,
                         "y":393.5
                        }, 
                        {
                         "height":0,
                         "id":33,
                         "name":"",
                         "point":true,
                         "rotation":0,
                         "type":"node",
                         "visible":true,
                         "width":0,
                         "x":318.5,
                         "y":569.5
                        }],
                 "opacity":1,
                 "type":"objectgroup",
                 "visible":true,
                 "x":0,
                 "y":0
                }, 
                {
                 "draworder":"topdown",
                 "id":9,
                 "name":"Top",
                 "objects":[
                        {
                         "height":0,
                         "id":34,
                         "name":"",
                         "polygon":[
                                {
                                 "x":4,
                                 "y":22
                                }, 
                                {
                                 "x":19,
                                 "y":148
                                }, 
                                {
                                 "x":11.5,
                                 "y":315.5
                                }, 
                                {
                                 "x":107,
                                 "y":256.5
                                }, 
                                {
                                 "x":242,
                                 "y":277
                                }, 
                                {
                                 "x":240,
                                 "y":227
                                }, 
                                {
                                 "x":218.5,
                                 "y":116.5
                                }, 
                                {
                                 "x":180,
                                 "y":18
                                }],
                         "rotation":0,
                         "type":"region",
                         "visible":true,
                         "width":0,
                         "x":217,
                         "y":-5.5
                        }, 
                        {
                         "height":0,
                         "id":35,
                         "name":"",
                         "point":true,
                         "rotation":0,
                         "type":"guard",
                         "visible":true,
                         "width":0,
                         "x":331.166666666667,
                         "y":209.166666666667
                        }, 
                        {
                         "height":0,
                         "id":36,
                         "name":"",
                         "point":true,
                         "rotation":0,
                         "type":"node",
                         "visible":true,
                         "width":0,
                         "x":342.833333333333,
                         "y":135.166666666667
                        }, 
                        {
                         "height":0,
                         "id":37,
                         "name":"",
                         "point":true,
                         "rotation":0,
                         "type":"node",
                         "visible":true,
                         "width":0,
                         "x":310.5,
                         "y":65.3333333333333
                        }],
                 "opacity":1,
                 "type":"objectgroup",
                 "visible":true,
                 "x":0,
                 "y":0
                }, 
                {
                 "draworder":"topdown",
                 "id":4,
                 "name":"Right",
                 "objects":[
                        {
                         "height":0,
                         "id":8,
                         "name":"right",
                         "polygon":[
                                {
                                 "x":-36.3333333333334,
                                 "y":-43.3333333333333
                                }, 
                                {
                                 "x":-161.764666666667,
                                 "y":-105.816296666667
                                }, 
                                {
                                 "x":-179.877,
                                 "y":-44.9392333333334
                                }, 
                                {
                                 "x":-157.417333333333,
                                 "y":79.7976666666667
                                }, 
                                {
                                 "x":-158.774333333333,
                                 "y":175.866333333333
                                }, 
                                {
                                 "x":-174.299666666666,
                                 "y":270.395
                                }, 
                                {
                                 "x":-143.457,
                                 "y":381.130333333334
                                }, 
                                {
                                 "x":-53.866666666667,
                                 "y":356.356333333333
                                }, 
                                {
                                 "x":-19.6874999999999,
                                 "y":150.267833333333
                                }],
                         "rotation":0,
                         "type":"region",
                         "visible":true,
                         "width":0,
                         "x":642.333333333333,
                         "y":153
                        }, 
                        {
                         "height":0,
                         "id":14,
                         "name":"2",
                         "point":true,
                         "rotation":0,
                         "type":"node",
                         "visible":true,
                         "width":0,
                         "x":516.666666666666,
                         "y":331.333333333333
                        }, 
                        {
                         "height":0,
                         "id":15,
                         "name":"1",
                         "point":true,
                         "rotation":0,
                         "type":"node",
                         "visible":true,
                         "width":0,
                         "x":553.333333333334,
                         "y":231.666666666667
                        }, 
                        {
                         "height":0,
                         "id":16,
                         "name":"3",
                         "point":true,
                         "rotation":0,
                         "type":"node",
                         "visible":true,
                         "width":0,
                         "x":530,
                         "y":455.333333333334
                        }, 
                        {
                         "height":0,
                         "id":28,
                         "name":"",
                         "point":true,
                         "rotation":0,
                         "type":"guard",
                         "visible":true,
                         "width":0,
                         "x":582.833333333333,
                         "y":356.25
                        }],
                 "opacity":1,
                 "properties":[
                        {
                         "name":"player_id",
                         "type":"int",
                         "value":1
                        }],
                 "type":"objectgroup",
                 "visible":true,
                 "x":0,
                 "y":0
                }, 
                {
                 "draworder":"topdown",
                 "id":3,
                 "name":"Left",
                 "objects":[
                        {
                         "height":0,
                         "id":1,
                         "name":"left",
                         "polygon":[
                                {
                                 "x":6.47329501227467,
                                 "y":162.1497884935
                                }, 
                                {
                                 "x":58.0731058178417,
                                 "y":267.930134675091
                                }, 
                                {
                                 "x":132.632836357104,
                                 "y":288.398958146219
                                }, 
                                {
                                 "x":164.496557092389,
                                 "y":248.754385964913
                                }, 
                                {
                                 "x":192.70182945243,
                                 "y":150.487575594275
                                }, 
                                {
                                 "x":196.175289346149,
                                 "y":60.3781174937889
                                }, 
                                {
                                 "x":187.538819279762,
                                 "y":-21.2156051009706
                                }, 
                                {
                                 "x":104.481917691758,
                                 "y":-84.6993852400285
                                }, 
                                {
                                 "x":-2.26818753368054,
                                 "y":-65.764505119454
                                }],
                         "rotation":0,
                         "type":"region",
                         "visible":true,
                         "width":0,
                         "x":17.2681875336806,
                         "y":184.281540027543
                        }, 
                        {
                         "height":0,
                         "id":10,
                         "name":"2",
                         "point":true,
                         "rotation":0,
                         "type":"node",
                         "visible":true,
                         "width":0,
                         "x":156.333333333333,
                         "y":314.333333333333
                        }, 
                        {
                         "height":0,
                         "id":11,
                         "name":"3",
                         "point":true,
                         "rotation":0,
                         "type":"node",
                         "visible":true,
                         "width":0,
                         "x":101.333333333333,
                         "y":418.333333333333
                        }, 
                        {
                         "height":0,
                         "id":12,
                         "name":"1",
                         "point":true,
                         "rotation":0,
                         "type":"node",
                         "visible":true,
                         "width":0,
                         "x":107.333333333333,
                         "y":165.666666666667
                        }, 
                        {
                         "height":0,
                         "id":27,
                         "name":"",
                         "point":true,
                         "rotation":0,
                         "type":"guard",
                         "visible":true,
                         "width":0,
                         "x":86.0833333333333,
                         "y":282
                        }],
                 "opacity":1,
                 "properties":[
                        {
                         "name":"player_id",
                         "type":"int",
                         "value":2
                        }],
                 "type":"objectgroup",
                 "visible":true,
                 "x":0,
                 "y":0
                }],
         "name":"Regions",
         "opacity":1,
         "type":"group",
         "visible":true,
         "x":0,
         "y":0
        }, 
        {
         "draworder":"topdown",
         "id":7,
         "name":"Paths",
         "objects":[
                {
                 "height":0,
                 "id":17,
                 "name":"1",
                 "polyline":[
                        {
                         "x":150.666666666666,
                         "y":1.3333333333334
                        }, 
                        {
                         "x":120,
                         "y":-15.6666666666667
                        }, 
                        {
                         "x":84.333333333333,
                         "y":-4.6666666666667
                        }],
                 "rotation":0,
                 "type":"road",
                 "visible":true,
                 "width":0,
                 "x":98.6666666666667,
                 "y":171.666666666667
                }, 
                {
                 "height":0,
                 "id":18,
                 "name":"2",
                 "polyline":[
                        {
                         "x":74.6666666666667,
                         "y":247.666666666667
                        }, 
                        {
                         "x":103.333333333333,
                         "y":268
                        }, 
                        {
                         "x":147.333333333333,
                         "y":290.333333333333
                        }],
                 "rotation":0,
                 "type":"road",
                 "visible":true,
                 "width":0,
                 "x":78.6666666666667,
                 "y":190
                }, 
                {
                 "height":0,
                 "id":38,
                 "name":"",
                 "polyline":[
                        {
                         "x":0,
                         "y":0
                        }, 
                        {
                         "x":33,
                         "y":1.33333333333334
                        }, 
                        {
                         "x":63.6666666666667,
                         "y":18.6666666666667
                        }],
                 "rotation":0,
                 "type":"road",
                 "visible":true,
                 "width":0,
                 "x":425.333333333333,
                 "y":149.666666666667
                }, 
                {
                 "height":0,
                 "id":39,
                 "name":"",
                 "polyline":[
                        {
                         "x":0,
                         "y":0
                        }, 
                        {
                         "x":24,
                         "y":-3
                        }, 
                        {
                         "x":47.3333333333333,
                         "y":7.33333333333331
                        }],
                 "rotation":0,
                 "type":"road",
                 "visible":true,
                 "width":0,
                 "x":429.69696969697,
                 "y":415.969696969697
                }],
         "opacity":1,
         "type":"objectgroup",
         "visible":true,
         "x":0,
         "y":0
        }],
 "nextlayerid":10,
 "nextobjectid":40,
 "orientation":"orthogonal",
 "properties":[
        {
         "name":"name",
         "type":"string",
         "value":"Duel"
        }, 
        {
         "name":"player_count",
         "type":"int",
         "value":2
        }],
 "renderorder":"right-down",
 "tiledversion":"1.10.2",
 "tileheight":32,
 "tilesets":[],
 "tilewidth":32,
 "type":"map",
 "version":"1.10",
 "width":20
}